blowdrycss/__init__.py
blowdrycss/blowdry.py
blowdrycss/blowdrycss_settings.py
blowdrycss/breakpointparser.py
blowdrycss/classparser.py
blowdrycss/classpropertyparser.py
blowdrycss/colorparser.py
blowdrycss/cssbuilder.py
blowdrycss/cssvalueparser.py
blowdrycss/datalibrary.py
blowdrycss/filehandler.py
blowdrycss/fontparser.py
blowdrycss/log.py
blowdrycss/mediaquerybuilder.py
blowdrycss/scalingparser.py
blowdrycss/settingsbuilder.py
blowdrycss/timing.py
blowdrycss/unitparser.py
blowdrycss/utilities.py
blowdrycss/watchdogwrapper.py
blowdrycss/unit_tests/__init__.py
blowdrycss/unit_tests/test_BreakpointParser.py
blowdrycss/unit_tests/test_CSSBuilder.py
blowdrycss/unit_tests/test_CSSFile.py
blowdrycss/unit_tests/test_CSSPropertyValueParser.py
blowdrycss/unit_tests/test_FileConverter.py
blowdrycss/unit_tests/test_FileFinder.py
blowdrycss/unit_tests/test_FileModificationComparator.py
blowdrycss/unit_tests/test_GenericFile.py
blowdrycss/unit_tests/test_ScalingParser.py
blowdrycss/unit_tests/test_all.py
blowdrycss/unit_tests/test_blowdry.py
blowdrycss/unit_tests/test_classExtractor.py
blowdrycss/unit_tests/test_classParser.py
blowdrycss/unit_tests/test_classPropertyParser.py
blowdrycss/unit_tests/test_colorParser.py
blowdrycss/unit_tests/test_dataLibrary.py
blowdrycss/unit_tests/test_fileRegexMap.py
blowdrycss/unit_tests/test_fontParser.py
blowdrycss/unit_tests/test_log.py
blowdrycss/unit_tests/test_mediaQueryBuilder.py
blowdrycss/unit_tests/test_timing.py
blowdrycss/unit_tests/test_tox_cleanup.py
blowdrycss/unit_tests/test_unitParser.py
blowdrycss/unit_tests/test_utilities.py
blowdrycss/unit_tests/test_version.py
blowdrycss/unit_tests/test_watchdog_fileEditEventHandler.py
blowdrycss/unit_tests/test_watchdogwrapper_main.py
blowdrycss/unit_tests/test_write_blowdrycss_settings_dot_py.py
blowdrycss/unit_tests/unittest_settings.py
blowdrycss-1.0.3.dist-info/DESCRIPTION.rst
blowdrycss-1.0.3.dist-info/METADATA
blowdrycss-1.0.3.dist-info/RECORD
blowdrycss-1.0.3.dist-info/WHEEL
blowdrycss-1.0.3.dist-info/entry_points.txt
blowdrycss-1.0.3.dist-info/metadata.json
blowdrycss-1.0.3.dist-info/top_level.txt
