Metadata-Version: 2.0
Name: blowdrycss
Version: 1.0.3
Summary: The atomic CSS compiler
Home-page: http://blowdrycss.org
Author: chad nelson
Author-email: nu.everest@gmail.com
License: MIT
Download-URL: https://github.com/nueverest/blowdrycss/archive/master.zip
Keywords: blowdry blowdrycss css compiler pre-compiler pre-processor generator dry cascading style sheets html encoded class selector parser optimizer internet
Platform: UNKNOWN
Classifier: Development Status :: 4 - Beta
Classifier: Intended Audience :: Developers
Classifier: Intended Audience :: Information Technology
Classifier: Natural Language :: English
Classifier: Operating System :: OS Independent
Classifier: Topic :: Artistic Software
Classifier: Topic :: Internet
Classifier: Topic :: Internet :: WWW/HTTP
Classifier: Topic :: Internet :: WWW/HTTP :: Dynamic Content
Classifier: Topic :: Internet :: WWW/HTTP :: Site Management
Classifier: Topic :: Software Development
Classifier: Topic :: Software Development :: Build Tools
Classifier: Topic :: Software Development :: Code Generators
Classifier: Topic :: Software Development :: Compilers
Classifier: Topic :: Software Development :: Pre-processors
Classifier: Topic :: Text Processing
Classifier: Topic :: Text Processing :: Filters
Classifier: Topic :: Text Processing :: General
Classifier: Topic :: Text Processing :: Markup
Classifier: Topic :: Text Processing :: Markup :: HTML
Classifier: Topic :: Utilities
Classifier: License :: OSI Approved :: MIT License
Classifier: Programming Language :: Python :: 2
Classifier: Programming Language :: Python :: 2.7
Classifier: Programming Language :: Python :: 3
Classifier: Programming Language :: Python :: 3.3
Classifier: Programming Language :: Python :: 3.4
Classifier: Programming Language :: Python :: 3.5
Classifier: Programming Language :: Python :: 3.6
Requires-Dist: cssutils (>=1.0.2)
Requires-Dist: pypandoc (>=1.4)
Requires-Dist: future (>=0.16.0)
Requires-Dist: watchdog (>=0.8.3)
Provides-Extra: development
Requires-Dist: sphinx (>=1.3.3); extra == 'development'
Requires-Dist: tox (>=2.3.1); extra == 'development'
Requires-Dist: coverage (>=4.0.2); extra == 'development'
Requires-Dist: wheel (>=0.26.0); extra == 'development'
Requires-Dist: twine (>=1.6.5); extra == 'development'
Provides-Extra: docs
Requires-Dist: sphinx (>=1.3.3); extra == 'docs'
Provides-Extra: testing
Requires-Dist: coverage (>=4.0.2); extra == 'testing'
Requires-Dist: tox (>=2.3.1); extra == 'testing'
